async_gsm_modem/__init__.py
async_gsm_modem/base/__init__.py
async_gsm_modem/base/command.py
async_gsm_modem/base/exceptions.py
async_gsm_modem/base/modem.py
async_gsm_modem/base/pdu.py
async_gsm_modem/base/response.py
async_gsm_modem/quectel_ec25/__init__.py
async_gsm_modem/quectel_ec25/constants.py
async_gsm_modem/quectel_ec25/exceptions.py
async_gsm_modem/quectel_ec25/info.py
async_gsm_modem/quectel_ec25/modem.py
async_gsm_modem/quectel_ec25/sms.py
async_gsm_modem-0.1.2.dist-info/LICENSE
async_gsm_modem-0.1.2.dist-info/METADATA
async_gsm_modem-0.1.2.dist-info/WHEEL
async_gsm_modem-0.1.2.dist-info/top_level.txt
async_gsm_modem-0.1.2.dist-info/RECORD
