Metadata-Version: 2.1
Name: async-gsm-modem
Version: 0.1.2
Summary: An async GSM modem driver library
Home-page: https://github.com/Sinusoidal36/async-gsm-modem
Author: sinusoidal
Author-email: 
License: UNKNOWN
Keywords: gsm,modem,asyncio,async,lte,sms,text,usb,serial,phone,mobile,messaging
Platform: UNKNOWN
Classifier: Programming Language :: Python :: 3
Classifier: Operating System :: OS Independent
Requires-Python: >=3.6
Requires-Dist: pyserial-asyncio
Requires-Dist: smspdudecoder
Requires-Dist: pydantic
